rotarysaw/__init__.py
rotarysaw/basic.py
rotarysaw/ca.crt
rotarysaw/colorlog.py
rotarysaw/gl.py
rotarysaw/heavyscience.py
rotarysaw/heavyscienceforce.py
rotarysaw/import_or_die.py
rotarysaw/log.py
rotarysaw/measure.py
rotarysaw/pyqt6.py
rotarysaw/pyqt63d.py
rotarysaw/pyqt6network.py
rotarysaw/science.py
rotarysaw/scienceforce.py
rotarysaw/simplemqtt.py
rotarysaw/test_rotarysaw.py
rotarysaw/timeout.py
rotarysaw/webcrawl.py
rotarysaw-666.39.2077.10.dist-info/LICENSE
rotarysaw-666.39.2077.10.dist-info/METADATA
rotarysaw-666.39.2077.10.dist-info/WHEEL
rotarysaw-666.39.2077.10.dist-info/top_level.txt
rotarysaw-666.39.2077.10.dist-info/RECORD
