Metadata-Version: 2.1
Name: rotarysaw
Version: 666.39.2077.10
Summary: Rotary Saw
Author: Kuu Tirronen
Author-email: <kuu@uraanikaivos.fi>
Keywords: python,turrican,rotary saw,tirronen,rotarysaw
Classifier: Development Status :: 5 - Production/Stable
Classifier: Natural Language :: English
Classifier: Operating System :: OS Independent
Classifier: Programming Language :: Python :: 3.11
License-File: LICENSE
Requires-Dist: tabulate
Requires-Dist: pytest
Requires-Dist: pytest-mock
